README.md
setup.py
sciapp/__init__.py
sciapp/app.py
sciapp/manager.py
sciapp/action/__init__.py
sciapp/action/action.py
sciapp/action/imgact.py
sciapp/action/tabact.py
sciapp/action/tolact.py
sciapp/action/advanced/__init__.py
sciapp/action/advanced/dataio.py
sciapp/action/advanced/filter.py
sciapp/action/advanced/free.py
sciapp/action/advanced/macros.py
sciapp/action/advanced/simple.py
sciapp/action/advanced/table.py
sciapp/action/advanced/widget.py
sciapp/action/plugin/__init__.py
sciapp/action/plugin/filters.py
sciapp/action/plugin/generalio.py
sciapp/action/plugin/mea_tools.py
sciapp/action/plugin/roi_tools.py
sciapp/action/plugin/shp_tools.py
sciapp/action/plugin/shpbase.py
sciapp/object/__init__.py
sciapp/object/image.py
sciapp/object/roi.py
sciapp/object/shape.py
sciapp/object/surface.py
sciapp/object/table.py
sciapp/util/__init__.py
sciapp/util/imgutil.py
sciapp/util/shputil.py
sciapp/util/surfutil.py
scitk/__init__.py
scitk.egg-info/PKG-INFO
scitk.egg-info/SOURCES.txt
scitk.egg-info/dependency_links.txt
scitk.egg-info/requires.txt
scitk.egg-info/top_level.txt
scitk/app/__init__.py
scitk/app/imgapp.py
scitk/app/manager.py
scitk/app/module1.py
scitk/app/sciapp.py
scitk/canvas/__init__.py
scitk/canvas/boxutil.py
scitk/canvas/canvas (复件).py
scitk/canvas/canvas.py
scitk/canvas/imutil.py
scitk/canvas/mcanvas.py
scitk/canvas/widget.py
scitk/grid/__init__.py
scitk/grid/grid.py
scitk/grid/widget.py
scitk/mesh/__init__.py
scitk/mesh/canvas.py
scitk/mesh/module1.py
scitk/plot/__init__.py
scitk/plot/plot.py
scitk/plugins/__init__.py
scitk/plugins/filters.py
scitk/text/__init__.py
scitk/text/mdpad.py
scitk/text/mdutil.py
scitk/text/textpad.py
scitk/widgets/__init__.py
scitk/widgets/choicebook.py
scitk/widgets/controls.py
scitk/widgets/curvepanel.py
scitk/widgets/guiflow.py
scitk/widgets/menubar.py
scitk/widgets/normal.py
scitk/widgets/paradialog.py
scitk/widgets/scrollabletreeviewframe.py
scitk/widgets/toolbar.py
scitk/widgets/workflow.py
scitk/widgets/tkwidgetext/__init__.py
scitk/widgets/tkwidgetext/choicebook.py
scitk/widgets/tkwidgetext/closablenotebook.py
scitk/widgets/tkwidgetext/scrolledcanvas.py
