Metadata-Version: 1.0
Name: scitk
Version: 0.0.2
Summary: python GUI framework like sciwx,  based on tkinter, pillow(PIL) and various of functional libs
Home-page: https://gitee.com/hzy15610046011/scitk
Author: Zhanyi Hou
Author-email: 3120388018@qq.com
License: MuLan2.0
Platform: UNKNOWN
